keyrock_encryption/__init__.py
keyrock_encryption/encryption/__init__.py
keyrock_encryption/encryption/encryption.py
keyrock_encryption/encryption/test_encryption.py
keyrock_encryption-2024.2.15.1117.dist-info/METADATA
keyrock_encryption-2024.2.15.1117.dist-info/WHEEL
keyrock_encryption-2024.2.15.1117.dist-info/top_level.txt
keyrock_encryption-2024.2.15.1117.dist-info/RECORD
