Metadata-Version: 2.1
Name: keyrock-encryption
Version: 2024.2.15.1117
Requires-Dist: keyrock-core
Requires-Dist: pycryptodome ==3.20.0
